spectrum_data_loader/__init__.py
spectrum_data_loader/parser.py
spectrum_data_loader-0.1.3.dist-info/licenses/LICENCE.txt
spectrum_data_loader-0.1.3.dist-info/METADATA
spectrum_data_loader-0.1.3.dist-info/WHEEL
spectrum_data_loader-0.1.3.dist-info/top_level.txt
spectrum_data_loader-0.1.3.dist-info/RECORD
